autoreduce_frontend/__init__.py
autoreduce_frontend/clear_db_objects.py
autoreduce_frontend/manage.py
autoreduce_frontend/autoreduce_webapp/__init__.py
autoreduce_frontend/autoreduce_webapp/admin.py
autoreduce_frontend/autoreduce_webapp/backends.py
autoreduce_frontend/autoreduce_webapp/context_processors.py
autoreduce_frontend/autoreduce_webapp/icat_cache.py
autoreduce_frontend/autoreduce_webapp/icat_communication.py
autoreduce_frontend/autoreduce_webapp/models.py
autoreduce_frontend/autoreduce_webapp/settings.py
autoreduce_frontend/autoreduce_webapp/uows_client.py
autoreduce_frontend/autoreduce_webapp/urls.py
autoreduce_frontend/autoreduce_webapp/view_utils.py
autoreduce_frontend/autoreduce_webapp/views.py
autoreduce_frontend/autoreduce_webapp/wsgi.py
autoreduce_frontend/autoreduce_webapp/management/__init__.py
autoreduce_frontend/autoreduce_webapp/management/commands/__init__.py
autoreduce_frontend/autoreduce_webapp/management/commands/add_super.py
autoreduce_frontend/autoreduce_webapp/migrations/0001_initial.py
autoreduce_frontend/autoreduce_webapp/migrations/__init__.py
autoreduce_frontend/autoreduce_webapp/templatetags/__init__.py
autoreduce_frontend/autoreduce_webapp/templatetags/colour_table_rows.py
autoreduce_frontend/autoreduce_webapp/templatetags/common_helpers.py
autoreduce_frontend/autoreduce_webapp/templatetags/natural_time_difference.py
autoreduce_frontend/autoreduce_webapp/templatetags/replace.py
autoreduce_frontend/autoreduce_webapp/templatetags/variable_type.py
autoreduce_frontend/autoreduce_webapp/templatetags/view.py
autoreduce_frontend/instrument/__init__.py
autoreduce_frontend/instrument/admin.py
autoreduce_frontend/instrument/urls.py
autoreduce_frontend/instrument/views/__init__.py
autoreduce_frontend/instrument/views/pause.py
autoreduce_frontend/instrument/views/runs.py
autoreduce_frontend/instrument/views/variables.py
autoreduce_frontend/plotting/__init__.py
autoreduce_frontend/plotting/plot_handler.py
autoreduce_frontend-21.1.3.dist-info/LICENSE.txt
autoreduce_frontend-21.1.3.dist-info/METADATA
autoreduce_frontend-21.1.3.dist-info/WHEEL
autoreduce_frontend-21.1.3.dist-info/entry_points.txt
autoreduce_frontend-21.1.3.dist-info/top_level.txt
autoreduce_frontend-21.1.3.dist-info/RECORD
