Metadata-Version: 2.1
Name: autoreduce-frontend
Version: 21.1.3
Summary: The frontend of the ISIS Autoreduction service
Home-page: https://github.com/ISISScientificComputing/autoreduce-frontend/
Author: ISIS Autoreduction Team
Author-email: UNKNOWN
License: UNKNOWN
Platform: UNKNOWN
Requires-Dist: autoreduce-utils (==0.1.3)
Requires-Dist: autoreduce-db (==0.1.4)
Requires-Dist: autoreduce-qp (==21.1.3)
Requires-Dist: Django (==3.2.2)
Requires-Dist: django-extensions (==3.1.3)
Requires-Dist: django-user-agents (==0.4.0)
